pypeline/__init__.py
pypeline/barrier.py
pypeline/composition.py
pypeline/constants.py
pypeline/dramatiq.py
pypeline/extensions.py
pypeline/middleware.py
pypeline/pipeline_config_schema.py
pypeline/pypeline_yaml.py
pypeline/schedule_config_schema.py
pypeline/flask/__init__.py
pypeline/flask/decorators.py
pypeline/flask/flask_pypeline.py
pypeline/flask/api/__init__.py
pypeline/flask/api/pipelines.py
pypeline/flask/api/schedules.py
pypeline/utils/__init__.py
pypeline/utils/config_utils.py
pypeline/utils/module_utils.py
pypeline/utils/pipeline_utils.py
tests/fixtures/__init__.py
scalable_pypeline-3.0.1.dist-info/LICENSE
scalable_pypeline-3.0.1.dist-info/METADATA
scalable_pypeline-3.0.1.dist-info/WHEEL
scalable_pypeline-3.0.1.dist-info/entry_points.txt
scalable_pypeline-3.0.1.dist-info/top_level.txt
scalable_pypeline-3.0.1.dist-info/RECORD
