Metadata-Version: 2.1
Name: scalable-pypeline
Version: 3.0.1
Summary: PypeLine - Python pipelines for the Real World
Home-page: https://gitlab.com/bravos2/pypeline
Author: Bravos Power Corporation
License: Apache License 2.0
License-File: LICENSE
Requires-Dist: PyYAML (<7,>=6.0.1)
Requires-Dist: redis (<5,>=4.5.4)
Requires-Dist: db-medley[redis] (<2,>=1.0.2)
Requires-Dist: croniter (<2,>=1.0.15)
Provides-Extra: build
Requires-Dist: wheel ; extra == 'build'
Requires-Dist: twine ; extra == 'build'
Provides-Extra: dev
Requires-Dist: black ; extra == 'dev'
Provides-Extra: flask
Requires-Dist: flask-smorest (<0.45,>=0.44.0) ; extra == 'flask'
Requires-Dist: werkzeug (<4,>=3.0.1) ; extra == 'flask'
Requires-Dist: flask (<4,>=3.0.2) ; extra == 'flask'
Provides-Extra: test
Requires-Dist: pytest-cov (<3,>=2.6.1) ; extra == 'test'
Requires-Dist: tox (<4,>=3.14.1) ; extra == 'test'
Requires-Dist: mock (<2,>=1) ; extra == 'test'
Requires-Dist: responses (<0.11,>=0.10.16) ; extra == 'test'
Requires-Dist: fakeredis (<3,>=2.10.3) ; extra == 'test'
Requires-Dist: importlib-metadata (<5,>=4.12) ; extra == 'test'
Provides-Extra: web
Requires-Dist: gunicorn ; extra == 'web'
Requires-Dist: gevent (<22,>=21.12.0) ; extra == 'web'
Provides-Extra: workers
Requires-Dist: networkx (>=2.4) ; extra == 'workers'
Requires-Dist: dramatiq[rabbitmq] (<2,>=1.17.0) ; extra == 'workers'
Requires-Dist: apscheduler (<4,>=3.10.4) ; extra == 'workers'
